<?xml version="1.0" encoding="UTF-8"?>
<config>
	<matchRule>
		<matchCriteria>
			<nodeAddress>LOCAL</nodeAddress>
			<componentType>org.netbeams.dsp.demo.stocks.producer
			</componentType>
			<!-- <messageType>org.dsp.message.CreateMessage</messageType> -->
		</matchCriteria>
		<matchTarget>

			<nodeAddress>LOCAL</nodeAddress>
			<componentType>org.netbeams.dsp.demo.stocks.consumer
			</componentType>
		</matchTarget>
	</matchRule>
	<matchRule>
		<matchCriteria>
			<nodeAddress>LOCAL</nodeAddress>
			<componentType>org.netbeams.dsp.demo.stocks.producer
			</componentType>
			<!-- <messageType>org.dsp.message.CreateMessage</messageType> -->
		</matchCriteria>
		<matchTarget>

			<nodeAddress>LOCAL</nodeAddress>
			<componentType>org.netbeams.dsp.weblogger
			</componentType>
		</matchTarget>
	</matchRule>
	<matchRule>
		<matchCriteria>
			<nodeAddress>LOCAL</nodeAddress>

			<componentType>ALL</componentType>
			<!-- <messageType>org.dsp.message.CreateMessage</messageType> -->
		</matchCriteria>
		<matchTarget>
			<nodeAddress>LOCAL</nodeAddress>
			<componentType>org.netbeams.dsp.platform.channel
			</componentType>
		</matchTarget>
	</matchRule>
</config>